README.txt
bootstrap.py
buildout.cfg
setup.py
docs/HISTORY.txt
src/collective/__init__.py
src/collective.gsqi.egg-info/PKG-INFO
src/collective.gsqi.egg-info/SOURCES.txt
src/collective.gsqi.egg-info/dependency_links.txt
src/collective.gsqi.egg-info/entry_points.txt
src/collective.gsqi.egg-info/namespace_packages.txt
src/collective.gsqi.egg-info/not-zip-safe
src/collective.gsqi.egg-info/requires.txt
src/collective.gsqi.egg-info/top_level.txt
src/collective/gsqi/README.txt
src/collective/gsqi/__init__.py
src/collective/gsqi/configure.zcml
src/collective/gsqi/gs.py
src/collective/gsqi/gs.txt
src/collective/gsqi/overrides.zcml
src/collective/gsqi/qi.py
src/collective/gsqi/tests.py
src/collective/gsqi/content/__init__.py
src/collective/gsqi/content/common.py
src/collective/gsqi/content/field.py
src/collective/gsqi/content/index.py
src/collective/gsqi/content/layout.py
src/collective/gsqi/content/overrides.zcml
src/collective/gsqi/content/role.py
src/collective/gsqi/content/workflow.py
src/collective/gsqi/group/README.txt
src/collective/gsqi/group/__init__.py
src/collective/gsqi/group/configure.zcml
src/collective/gsqi/group/meta.py
src/collective/gsqi/group/tests.py
src/collective/gsqi/gsml/README.txt
src/collective/gsqi/gsml/__init__.py
src/collective/gsqi/gsml/meta.py
src/collective/gsqi/gsml/meta.zcml
src/collective/gsqi/gsml/testing.py
src/collective/gsqi/gsml/tests.py
src/collective/gsqi/refs/__init__.py
src/collective/gsqi/refs/configure.zcml
src/collective/gsqi/refs/meta.py
src/collective/gsqi/workflow/__init__.py
src/collective/gsqi/workflow/exportimport.py
src/collective/gsqi/workflow/overrides.zcml