Metadata-Version: 1.0
Name: collective.gsqi
Version: 0.3
Summary: Various GenericSetup handlers and CMFQuickInstaller enhancements
Home-page: http://pypi.python.org/pypi/collective.gsqi
Author: Ross Patterson
Author-email: me@rpatterson.net
License: GPL
Platform: UNKNOWN
Classifier: Programming Language :: Python
Classifier: Topic :: Software Development :: Libraries :: Python Modules
